{"type": "IssueCommentEvent", "actor": {"login": "mkcor"}, "repo": {"id": "33702544", "name": "plotly/dash"}, "payload": "\"{\"\"action\"\":\"\"created\"\"", "public": true, "created_at": "2019-09-23T12:40:55Z"}
{"type": "PullRequestEvent", "actor": {"login": "jbampton"}, "repo": {"id": "33702544", "name": "plotly/dash"}, "payload": "\"{\"\"action\"\":\"\"opened\"\"", "public": true, "created_at": "2019-09-23T15:06:31Z"}
{"type": "PullRequestEvent", "actor": {"login": "beckjake"}, "repo": {"id": "53548867", "name": "fishtown-analytics/dbt"}, "payload": "\"{\"\"action\"\":\"\"closed\"\"", "public": true, "created_at": "2019-09-23T15:54:29Z"}
{"type": "PullRequestEvent", "actor": {"login": "ryan-lane"}, "repo": {"id": "186647681", "name": "lyft/amundsen"}, "payload": "\"{\"\"action\"\":\"\"reopened\"\"", "public": true, "created_at": "2019-09-23T23:32:41Z"}
{"type": "ForkEvent", "actor": {"login": "sjc362000"}, "repo": {"id": "206444", "name": "apache/hive"}, "payload": "\"{\"\"forkee\"\":{\"\"id\"\":210407868", "public": true, "created_at": "2019-09-23T16:56:43Z"}
{"type": "PullRequestEvent", "actor": {"login": "ryan-lane"}, "repo": {"id": "186647681", "name": "lyft/amundsen"}, "payload": "\"{\"\"action\"\":\"\"reopened\"\"", "public": true, "created_at": "2019-09-23T23:32:10Z"}
{"type": "PushEvent", "actor": {"login": "feng-tao"}, "repo": {"id": "186647681", "name": "lyft/amundsen"}, "payload": "\"{\"\"push_id\"\":4067900068", "public": true, "created_at": "2019-09-23T23:45:04Z"}
{"type": "PushEvent", "actor": {"login": "beckjake"}, "repo": {"id": "53548867", "name": "fishtown-analytics/dbt"}, "payload": "\"{\"\"push_id\"\":4066135633", "public": true, "created_at": "2019-09-23T15:28:15Z"}
{"type": "WatchEvent", "actor": {"login": "JudyYe"}, "repo": {"id": "14579099", "name": "plotly/plotly.py"}, "payload": "\"{\"\"action\"\":\"\"started\"\"}\"", "public": true, "created_at": "2019-09-23T02:51:11Z"}
{"type": "DeleteEvent", "actor": {"login": "beckjake"}, "repo": {"id": "53548867", "name": "fishtown-analytics/dbt"}, "payload": "\"{\"\"ref\"\":\"\"feature/expose-cache-to-materializations\"\"", "public": true, "created_at": "2019-09-23T15:56:16Z"}
{"type": "CreateEvent", "actor": {"login": "byronz"}, "repo": {"id": "33702544", "name": "plotly/dash"}, "payload": "\"{\"\"ref\"\":\"\"testing-graph\"\"", "public": true, "created_at": "2019-09-23T17:44:39Z"}
{"type": "PushEvent", "actor": {"login": "mkcor"}, "repo": {"id": "33702544", "name": "plotly/dash"}, "payload": "\"{\"\"push_id\"\":4067117392", "public": true, "created_at": "2019-09-23T19:36:42Z"}
{"type": "PullRequestEvent", "actor": {"login": "ryan-lane"}, "repo": {"id": "186647681", "name": "lyft/amundsen"}, "payload": "\"{\"\"action\"\":\"\"closed\"\"", "public": true, "created_at": "2019-09-23T23:10:55Z"}
{"type": "PushEvent", "actor": {"login": "beckjake"}, "repo": {"id": "53548867", "name": "fishtown-analytics/dbt"}, "payload": "\"{\"\"push_id\"\":4066265109", "public": true, "created_at": "2019-09-23T15:56:13Z"}
{"type": "PullRequestEvent", "actor": {"login": "byronz"}, "repo": {"id": "33702544", "name": "plotly/dash"}, "payload": "\"{\"\"action\"\":\"\"opened\"\"", "public": true, "created_at": "2019-09-23T17:48:47Z"}
{"type": "PullRequestEvent", "actor": {"login": "alexcjohnson"}, "repo": {"id": "33702544", "name": "plotly/dash"}, "payload": "\"{\"\"action\"\":\"\"closed\"\"", "public": true, "created_at": "2019-09-23T15:18:00Z"}
{"type": "PushEvent", "actor": {"login": "asfgit"}, "repo": {"id": "206444", "name": "apache/hive"}, "payload": "\"{\"\"push_id\"\":4064532627", "public": true, "created_at": "2019-09-23T09:04:59Z"}
{"type": "WatchEvent", "actor": {"login": "jason-liew"}, "repo": {"id": "206444", "name": "apache/hive"}, "payload": "\"{\"\"action\"\":\"\"started\"\"}\"", "public": true, "created_at": "2019-09-23T16:44:19Z"}
{"type": "PushEvent", "actor": {"login": "alexcjohnson"}, "repo": {"id": "33702544", "name": "plotly/dash"}, "payload": "\"{\"\"push_id\"\":4066087067", "public": true, "created_at": "2019-09-23T15:18:06Z"}
{"type": "IssueCommentEvent", "actor": {"login": "emmanuelle"}, "repo": {"id": "14579099", "name": "plotly/plotly.py"}, "payload": "\"{\"\"action\"\":\"\"created\"\"", "public": true, "created_at": "2019-09-23T18:21:48Z"}
{"type": "IssueCommentEvent", "actor": {"login": "mkcor"}, "repo": {"id": "33702544", "name": "plotly/dash"}, "payload": "\"{\"\"action\"\":\"\"created\"\"", "public": true, "created_at": "2019-09-23T19:34:19Z"}
{"type": "CreateEvent", "actor": {"login": "dependabot-preview[bot]"}, "repo": {"id": "186647681", "name": "lyft/amundsen"}, "payload": "\"{\"\"ref\"\":\"\"dependabot/submodules/amundsensearchlibrary-ba666dc\"\"", "public": true, "created_at": "2019-09-23T19:31:45Z"}
{"type": "PullRequestEvent", "actor": {"login": "dependabot-preview[bot]"}, "repo": {"id": "186647681", "name": "lyft/amundsen"}, "payload": "\"{\"\"action\"\":\"\"opened\"\"", "public": true, "created_at": "2019-09-23T19:31:46Z"}
{"type": "IssuesEvent", "actor": {"login": "jornh"}, "repo": {"id": "186647681", "name": "lyft/amundsen"}, "payload": "\"{\"\"action\"\":\"\"opened\"\"", "public": true, "created_at": "2019-09-23T21:33:25Z"}
{"type": "WatchEvent", "actor": {"login": "blavoie"}, "repo": {"id": "186647681", "name": "lyft/amundsen"}, "payload": "\"{\"\"action\"\":\"\"started\"\"}\"", "public": true, "created_at": "2019-09-23T00:28:01Z"}
{"type": "PushEvent", "actor": {"login": "beckjake"}, "repo": {"id": "53548867", "name": "fishtown-analytics/dbt"}, "payload": "\"{\"\"push_id\"\":4066118212", "public": true, "created_at": "2019-09-23T15:24:28Z"}
{"type": "CreateEvent", "actor": {"login": "beckjake"}, "repo": {"id": "53548867", "name": "fishtown-analytics/dbt"}, "payload": "\"{\"\"ref\"\":\"\"fix/cleanup-dbt-help\"\"", "public": true, "created_at": "2019-09-23T20:52:20Z"}
{"type": "PullRequestReviewCommentEvent", "actor": {"login": "beckjake"}, "repo": {"id": "53548867", "name": "fishtown-analytics/dbt"}, "payload": "\"{\"\"action\"\":\"\"created\"\"", "public": true, "created_at": "2019-09-23T21:01:55Z"}
{"type": "WatchEvent", "actor": {"login": "AlexLenoir"}, "repo": {"id": "53548867", "name": "fishtown-analytics/dbt"}, "payload": "\"{\"\"action\"\":\"\"started\"\"}\"", "public": true, "created_at": "2019-09-23T21:41:06Z"}
{"type": "ForkEvent", "actor": {"login": "Vause"}, "repo": {"id": "206444", "name": "apache/hive"}, "payload": "\"{\"\"forkee\"\":{\"\"id\"\":210433068", "public": true, "created_at": "2019-09-23T19:13:21Z"}
{"type": "WatchEvent", "actor": {"login": "tabchas"}, "repo": {"id": "33702544", "name": "plotly/dash"}, "payload": "\"{\"\"action\"\":\"\"started\"\"}\"", "public": true, "created_at": "2019-09-23T21:22:14Z"}
{"type": "PullRequestEvent", "actor": {"login": "feng-tao"}, "repo": {"id": "186647681", "name": "lyft/amundsen"}, "payload": "\"{\"\"action\"\":\"\"reopened\"\"", "public": true, "created_at": "2019-09-23T23:07:34Z"}
{"type": "PullRequestEvent", "actor": {"login": "beckjake"}, "repo": {"id": "53548867", "name": "fishtown-analytics/dbt"}, "payload": "\"{\"\"action\"\":\"\"opened\"\"", "public": true, "created_at": "2019-09-23T18:43:47Z"}
{"type": "WatchEvent", "actor": {"login": "lithic"}, "repo": {"id": "14579099", "name": "plotly/plotly.py"}, "payload": "\"{\"\"action\"\":\"\"started\"\"}\"", "public": true, "created_at": "2019-09-23T15:11:59Z"}
{"type": "WatchEvent", "actor": {"login": "Blokje5"}, "repo": {"id": "53548867", "name": "fishtown-analytics/dbt"}, "payload": "\"{\"\"action\"\":\"\"started\"\"}\"", "public": true, "created_at": "2019-09-23T19:35:24Z"}
{"type": "CreateEvent", "actor": {"login": "beckjake"}, "repo": {"id": "53548867", "name": "fishtown-analytics/dbt"}, "payload": "\"{\"\"ref\"\":\"\"feature/validate-targets-programmatically\"\"", "public": true, "created_at": "2019-09-23T15:08:29Z"}
{"type": "IssueCommentEvent", "actor": {"login": "davidghill"}, "repo": {"id": "33702544", "name": "plotly/dash"}, "payload": "\"{\"\"action\"\":\"\"created\"\"", "public": true, "created_at": "2019-09-23T15:42:46Z"}
{"type": "PullRequestEvent", "actor": {"login": "dschaller"}, "repo": {"id": "186647681", "name": "lyft/amundsen"}, "payload": "\"{\"\"action\"\":\"\"reopened\"\"", "public": true, "created_at": "2019-09-23T22:47:53Z"}
{"type": "PushEvent", "actor": {"login": "emmanuelle"}, "repo": {"id": "14579099", "name": "plotly/plotly.py"}, "payload": "\"{\"\"push_id\"\":4066784794", "public": true, "created_at": "2019-09-23T18:08:55Z"}
{"type": "IssueCommentEvent", "actor": {"login": "drewbanin"}, "repo": {"id": "53548867", "name": "fishtown-analytics/dbt"}, "payload": "\"{\"\"action\"\":\"\"created\"\"", "public": true, "created_at": "2019-09-23T19:59:29Z"}
{"type": "DeleteEvent", "actor": {"login": "dependabot-preview[bot]"}, "repo": {"id": "186647681", "name": "lyft/amundsen"}, "payload": "\"{\"\"ref\"\":\"\"dependabot/submodules/amundsensearchlibrary-ba666dc\"\"", "public": true, "created_at": "2019-09-23T23:45:11Z"}
{"type": "PushEvent", "actor": {"login": "byronz"}, "repo": {"id": "33702544", "name": "plotly/dash"}, "payload": "\"{\"\"push_id\"\":4066721765", "public": true, "created_at": "2019-09-23T17:52:32Z"}
{"type": "WatchEvent", "actor": {"login": "mailan2008"}, "repo": {"id": "33702544", "name": "plotly/dash"}, "payload": "\"{\"\"action\"\":\"\"started\"\"}\"", "public": true, "created_at": "2019-09-23T20:38:34Z"}
{"type": "WatchEvent", "actor": {"login": "mitinarseny"}, "repo": {"id": "14579099", "name": "plotly/plotly.py"}, "payload": "\"{\"\"action\"\":\"\"started\"\"}\"", "public": true, "created_at": "2019-09-23T21:31:11Z"}
{"type": "PullRequestEvent", "actor": {"login": "feng-tao"}, "repo": {"id": "186647681", "name": "lyft/amundsen"}, "payload": "\"{\"\"action\"\":\"\"closed\"\"", "public": true, "created_at": "2019-09-23T22:33:00Z"}
{"type": "PullRequestEvent", "actor": {"login": "beckjake"}, "repo": {"id": "53548867", "name": "fishtown-analytics/dbt"}, "payload": "\"{\"\"action\"\":\"\"opened\"\"", "public": true, "created_at": "2019-09-23T21:01:03Z"}
{"type": "WatchEvent", "actor": {"login": "jrohmh"}, "repo": {"id": "186647681", "name": "lyft/amundsen"}, "payload": "\"{\"\"action\"\":\"\"started\"\"}\"", "public": true, "created_at": "2019-09-23T11:05:44Z"}
{"type": "PullRequestEvent", "actor": {"login": "ryan-lane"}, "repo": {"id": "186647681", "name": "lyft/amundsen"}, "payload": "\"{\"\"action\"\":\"\"reopened\"\"", "public": true, "created_at": "2019-09-23T23:10:57Z"}
{"type": "WatchEvent", "actor": {"login": "chwang1991"}, "repo": {"id": "14579099", "name": "plotly/plotly.py"}, "payload": "\"{\"\"action\"\":\"\"started\"\"}\"", "public": true, "created_at": "2019-09-23T08:18:36Z"}
{"type": "WatchEvent", "actor": {"login": "botheredbybees"}, "repo": {"id": "33702544", "name": "plotly/dash"}, "payload": "\"{\"\"action\"\":\"\"started\"\"}\"", "public": true, "created_at": "2019-09-23T00:10:40Z"}
{"type": "IssueCommentEvent", "actor": {"login": "dependabot-preview[bot]"}, "repo": {"id": "186647681", "name": "lyft/amundsen"}, "payload": "\"{\"\"action\"\":\"\"created\"\"", "public": true, "created_at": "2019-09-23T22:33:02Z"}
{"type": "WatchEvent", "actor": {"login": "DonjuanChu"}, "repo": {"id": "14579099", "name": "plotly/plotly.py"}, "payload": "\"{\"\"action\"\":\"\"started\"\"}\"", "public": true, "created_at": "2019-09-23T16:53:12Z"}
{"type": "PushEvent", "actor": {"login": "asfgit"}, "repo": {"id": "206444", "name": "apache/hive"}, "payload": "\"{\"\"push_id\"\":4065368229", "public": true, "created_at": "2019-09-23T12:48:03Z"}
{"type": "PullRequestEvent", "actor": {"login": "feng-tao"}, "repo": {"id": "186647681", "name": "lyft/amundsen"}, "payload": "\"{\"\"action\"\":\"\"reopened\"\"", "public": true, "created_at": "2019-09-23T22:59:46Z"}
{"type": "IssueCommentEvent", "actor": {"login": "jornh"}, "repo": {"id": "186647681", "name": "lyft/amundsen"}, "payload": "\"{\"\"action\"\":\"\"created\"\"", "public": true, "created_at": "2019-09-23T23:26:52Z"}
{"type": "PushEvent", "actor": {"login": "beckjake"}, "repo": {"id": "53548867", "name": "fishtown-analytics/dbt"}, "payload": "\"{\"\"push_id\"\":4066252740", "public": true, "created_at": "2019-09-23T15:53:30Z"}
{"type": "IssueCommentEvent", "actor": {"login": "rrbarbosa"}, "repo": {"id": "53548867", "name": "fishtown-analytics/dbt"}, "payload": "\"{\"\"action\"\":\"\"created\"\"", "public": true, "created_at": "2019-09-23T11:10:34Z"}
{"type": "ForkEvent", "actor": {"login": "scarlin-cloudera"}, "repo": {"id": "206444", "name": "apache/hive"}, "payload": "\"{\"\"forkee\"\":{\"\"id\"\":210409144", "public": true, "created_at": "2019-09-23T17:03:25Z"}
{"type": "WatchEvent", "actor": {"login": "aammjian"}, "repo": {"id": "33702544", "name": "plotly/dash"}, "payload": "\"{\"\"action\"\":\"\"started\"\"}\"", "public": true, "created_at": "2019-09-23T07:11:05Z"}
{"type": "PullRequestEvent", "actor": {"login": "scarlin-cloudera"}, "repo": {"id": "206444", "name": "apache/hive"}, "payload": "\"{\"\"action\"\":\"\"opened\"\"", "public": true, "created_at": "2019-09-23T17:50:59Z"}
{"type": "PushEvent", "actor": {"login": "asfgit"}, "repo": {"id": "206444", "name": "apache/hive"}, "payload": "\"{\"\"push_id\"\":4065269554", "public": true, "created_at": "2019-09-23T12:23:34Z"}
{"type": "CreateEvent", "actor": {"login": "beckjake"}, "repo": {"id": "53548867", "name": "fishtown-analytics/dbt"}, "payload": "\"{\"\"ref\"\":\"\"feature/partition-filters-sources\"\"", "public": true, "created_at": "2019-09-23T18:38:21Z"}
{"type": "ForkEvent", "actor": {"login": "sapphirus15"}, "repo": {"id": "33702544", "name": "plotly/dash"}, "payload": "\"{\"\"forkee\"\":{\"\"id\"\":210325883", "public": true, "created_at": "2019-09-23T10:19:02Z"}
{"type": "WatchEvent", "actor": {"login": "melaniemkwon"}, "repo": {"id": "53548867", "name": "fishtown-analytics/dbt"}, "payload": "\"{\"\"action\"\":\"\"started\"\"}\"", "public": true, "created_at": "2019-09-23T07:26:50Z"}
{"type": "WatchEvent", "actor": {"login": "jmcomber"}, "repo": {"id": "33702544", "name": "plotly/dash"}, "payload": "\"{\"\"action\"\":\"\"started\"\"}\"", "public": true, "created_at": "2019-09-23T20:22:33Z"}
{"type": "WatchEvent", "actor": {"login": "qiongxiao"}, "repo": {"id": "14579099", "name": "plotly/plotly.py"}, "payload": "\"{\"\"action\"\":\"\"started\"\"}\"", "public": true, "created_at": "2019-09-23T10:13:59Z"}
{"type": "PullRequestEvent", "actor": {"login": "feng-tao"}, "repo": {"id": "186647681", "name": "lyft/amundsen"}, "payload": "\"{\"\"action\"\":\"\"closed\"\"", "public": true, "created_at": "2019-09-23T23:45:03Z"}
{"type": "PushEvent", "actor": {"login": "asfgit"}, "repo": {"id": "206444", "name": "apache/hive"}, "payload": "\"{\"\"push_id\"\":4066810340", "public": true, "created_at": "2019-09-23T18:15:50Z"}
{"type": "WatchEvent", "actor": {"login": "collinzrj"}, "repo": {"id": "14579099", "name": "plotly/plotly.py"}, "payload": "\"{\"\"action\"\":\"\"started\"\"}\"", "public": true, "created_at": "2019-09-23T23:50:48Z"}
{"type": "PullRequestEvent", "actor": {"login": "ryan-lane"}, "repo": {"id": "186647681", "name": "lyft/amundsen"}, "payload": "\"{\"\"action\"\":\"\"closed\"\"", "public": true, "created_at": "2019-09-23T23:32:38Z"}
{"type": "WatchEvent", "actor": {"login": "jpuris"}, "repo": {"id": "33702544", "name": "plotly/dash"}, "payload": "\"{\"\"action\"\":\"\"started\"\"}\"", "public": true, "created_at": "2019-09-23T20:16:20Z"}
{"type": "PullRequestEvent", "actor": {"login": "ryan-lane"}, "repo": {"id": "186647681", "name": "lyft/amundsen"}, "payload": "\"{\"\"action\"\":\"\"closed\"\"", "public": true, "created_at": "2019-09-23T23:32:08Z"}
{"type": "PullRequestEvent", "actor": {"login": "beckjake"}, "repo": {"id": "53548867", "name": "fishtown-analytics/dbt"}, "payload": "\"{\"\"action\"\":\"\"opened\"\"", "public": true, "created_at": "2019-09-23T15:14:19Z"}
{"type": "PullRequestEvent", "actor": {"login": "feng-tao"}, "repo": {"id": "186647681", "name": "lyft/amundsen"}, "payload": "\"{\"\"action\"\":\"\"reopened\"\"", "public": true, "created_at": "2019-09-23T22:33:02Z"}
{"type": "PushEvent", "actor": {"login": "mkcor"}, "repo": {"id": "33702544", "name": "plotly/dash"}, "payload": "\"{\"\"push_id\"\":4067082103", "public": true, "created_at": "2019-09-23T19:27:18Z"}
{"type": "PushEvent", "actor": {"login": "jtcohen6"}, "repo": {"id": "53548867", "name": "fishtown-analytics/dbt"}, "payload": "\"{\"\"push_id\"\":4067541756", "public": true, "created_at": "2019-09-23T21:31:37Z"}
{"type": "PushEvent", "actor": {"login": "beckjake"}, "repo": {"id": "53548867", "name": "fishtown-analytics/dbt"}, "payload": "\"{\"\"push_id\"\":4067433541", "public": true, "created_at": "2019-09-23T21:00:28Z"}
{"type": "PullRequestEvent", "actor": {"login": "feng-tao"}, "repo": {"id": "186647681", "name": "lyft/amundsen"}, "payload": "\"{\"\"action\"\":\"\"closed\"\"", "public": true, "created_at": "2019-09-23T23:07:32Z"}
{"type": "WatchEvent", "actor": {"login": "cpnat"}, "repo": {"id": "186647681", "name": "lyft/amundsen"}, "payload": "\"{\"\"action\"\":\"\"started\"\"}\"", "public": true, "created_at": "2019-09-23T19:58:45Z"}
{"type": "WatchEvent", "actor": {"login": "jager9418"}, "repo": {"id": "33702544", "name": "plotly/dash"}, "payload": "\"{\"\"action\"\":\"\"started\"\"}\"", "public": true, "created_at": "2019-09-23T03:09:37Z"}
{"type": "WatchEvent", "actor": {"login": "Duchadian"}, "repo": {"id": "186647681", "name": "lyft/amundsen"}, "payload": "\"{\"\"action\"\":\"\"started\"\"}\"", "public": true, "created_at": "2019-09-23T08:02:05Z"}
{"type": "PullRequestEvent", "actor": {"login": "dschaller"}, "repo": {"id": "186647681", "name": "lyft/amundsen"}, "payload": "\"{\"\"action\"\":\"\"closed\"\"", "public": true, "created_at": "2019-09-23T22:47:51Z"}
{"type": "PullRequestEvent", "actor": {"login": "feng-tao"}, "repo": {"id": "186647681", "name": "lyft/amundsen"}, "payload": "\"{\"\"action\"\":\"\"closed\"\"", "public": true, "created_at": "2019-09-23T22:59:45Z"}
{"type": "IssueCommentEvent", "actor": {"login": "ssj30"}, "repo": {"id": "33702544", "name": "plotly/dash"}, "payload": "\"{\"\"action\"\":\"\"created\"\"", "public": true, "created_at": "2019-09-23T10:25:26Z"}
{"type": "IssueCommentEvent", "actor": {"login": "dschaller"}, "repo": {"id": "186647681", "name": "lyft/amundsen"}, "payload": "\"{\"\"action\"\":\"\"created\"\"", "public": true, "created_at": "2019-09-23T22:47:23Z"}
{"type": "PullRequestEvent", "actor": {"login": "miklosgergely"}, "repo": {"id": "206444", "name": "apache/hive"}, "payload": "\"{\"\"action\"\":\"\"opened\"\"", "public": true, "created_at": "2019-09-23T06:21:42Z"}
{"type": "PushEvent", "actor": {"login": "beckjake"}, "repo": {"id": "53548867", "name": "fishtown-analytics/dbt"}, "payload": "\"{\"\"push_id\"\":4066257335", "public": true, "created_at": "2019-09-23T15:54:31Z"}
{"type": "PushEvent", "actor": {"login": "byronz"}, "repo": {"id": "33702544", "name": "plotly/dash"}, "payload": "\"{\"\"push_id\"\":4066723354", "public": true, "created_at": "2019-09-23T17:52:56Z"}
{"type": "WatchEvent", "actor": {"login": "ciarans"}, "repo": {"id": "33702544", "name": "plotly/dash"}, "payload": "\"{\"\"action\"\":\"\"started\"\"}\"", "public": true, "created_at": "2019-09-23T11:06:48Z"}
{"type": "IssuesEvent", "actor": {"login": "beckjake"}, "repo": {"id": "53548867", "name": "fishtown-analytics/dbt"}, "payload": "\"{\"\"action\"\":\"\"closed\"\"", "public": true, "created_at": "2019-09-23T15:54:29Z"}
{"type": "ForkEvent", "actor": {"login": "jangocheng"}, "repo": {"id": "14579099", "name": "plotly/plotly.py"}, "payload": "\"{\"\"forkee\"\":{\"\"id\"\":210280239", "public": true, "created_at": "2019-09-23T06:28:09Z"}
{"type": "WatchEvent", "actor": {"login": "Bryan-Rojas"}, "repo": {"id": "33702544", "name": "plotly/dash"}, "payload": "\"{\"\"action\"\":\"\"started\"\"}\"", "public": true, "created_at": "2019-09-23T22:02:47Z"}
{"type": "PushEvent", "actor": {"login": "beckjake"}, "repo": {"id": "53548867", "name": "fishtown-analytics/dbt"}, "payload": "\"{\"\"push_id\"\":4066089246", "public": true, "created_at": "2019-09-23T15:18:31Z"}
{"type": "PushEvent", "actor": {"login": "emmanuelle"}, "repo": {"id": "14579099", "name": "plotly/plotly.py"}, "payload": "\"{\"\"push_id\"\":4067457236", "public": true, "created_at": "2019-09-23T21:06:54Z"}
